doccano_client/__init__.py
doccano_client/beta/README.md
doccano_client/beta/__init__.py
doccano_client/beta/client.py
doccano_client/beta/controllers/__init__.py
doccano_client/beta/controllers/annotation.py
doccano_client/beta/controllers/category.py
doccano_client/beta/controllers/category_type.py
doccano_client/beta/controllers/comment.py
doccano_client/beta/controllers/example.py
doccano_client/beta/controllers/label.py
doccano_client/beta/controllers/member.py
doccano_client/beta/controllers/project.py
doccano_client/beta/controllers/relation.py
doccano_client/beta/controllers/relation_type.py
doccano_client/beta/controllers/span.py
doccano_client/beta/controllers/span_type.py
doccano_client/beta/controllers/text.py
doccano_client/beta/models/__init__.py
doccano_client/beta/models/annotations.py
doccano_client/beta/models/category.py
doccano_client/beta/models/category_type.py
doccano_client/beta/models/comments.py
doccano_client/beta/models/examples.py
doccano_client/beta/models/labels.py
doccano_client/beta/models/members.py
doccano_client/beta/models/projects.py
doccano_client/beta/models/relation.py
doccano_client/beta/models/relation_type.py
doccano_client/beta/models/span.py
doccano_client/beta/models/span_type.py
doccano_client/beta/models/text.py
doccano_client/beta/py.typed
doccano_client/beta/tests/__init__.py
doccano_client/beta/tests/conftest.py
doccano_client/beta/tests/controllers/__init__.py
doccano_client/beta/tests/controllers/mock_api_responses/__init__.py
doccano_client/beta/tests/controllers/mock_api_responses/annotations.py
doccano_client/beta/tests/controllers/mock_api_responses/bad.py
doccano_client/beta/tests/controllers/mock_api_responses/categories.py
doccano_client/beta/tests/controllers/mock_api_responses/category_types.py
doccano_client/beta/tests/controllers/mock_api_responses/comments.py
doccano_client/beta/tests/controllers/mock_api_responses/examples.py
doccano_client/beta/tests/controllers/mock_api_responses/labels.py
doccano_client-1.2.8.dist-info/LICENSE
doccano_client-1.2.8.dist-info/METADATA
doccano_client-1.2.8.dist-info/WHEEL
doccano_client-1.2.8.dist-info/entry_points.txt
doccano_client-1.2.8.dist-info/RECORD
