Metadata-Version: 2.1
Name: doccano-client
Version: 1.2.8
Summary: A simple client for doccano API.
Home-page: https://github.com/doccano/doccano-client
License: MIT
Author: Hironsan
Author-email: hiroki.nakayama.py@gmail.com
Requires-Python: >=3.8,<4.0
Classifier: License :: OSI Approved :: MIT License
Classifier: Programming Language :: Python
Classifier: Programming Language :: Python :: 3
Classifier: Programming Language :: Python :: 3.8
Classifier: Programming Language :: Python :: 3.9
Classifier: Programming Language :: Python :: 3.10
Classifier: Programming Language :: Python :: 3.11
Classifier: Programming Language :: Python :: Implementation :: CPython
Provides-Extra: al
Provides-Extra: spacy
Provides-Extra: whisper
Requires-Dist: dataclasses-json (>=0.5.7,<0.6.0)
Requires-Dist: ffmpeg-python (>=0.2.0,<0.3.0) ; extra == "whisper"
Requires-Dist: pandas (>=1.5.1,<2.0.0) ; extra == "al"
Requires-Dist: pydantic (>=1.9.2,<2.0.0)
Requires-Dist: requests (>=2.28.1,<3.0.0)
Requires-Dist: requests-toolbelt (>=0.9.1,<0.10.0)
Requires-Dist: seqal (>=0.3.4,<0.4.0) ; extra == "al"
Requires-Dist: spacy (>=3.4.1,<4.0.0) ; extra == "spacy" or extra == "al"
Requires-Dist: spacy-partial-tagger (>=0.9.1,<0.10.0) ; extra == "spacy"
Requires-Dist: tqdm (>=4.64.1,<5.0.0) ; extra == "spacy" or extra == "whisper"
Project-URL: Repository, https://github.com/doccano/doccano-client
